nessus/__init__.py
nessus/api.py
nessus/constants.py
nessus/exceptions.py
nessus/export.py
nessus/models.py
nessus/tests/__init__.py
nessus/tests/test_api.py
nessus_py-1.2.1.dist-info/METADATA
nessus_py-1.2.1.dist-info/WHEEL
nessus_py-1.2.1.dist-info/RECORD
