Metadata-Version: 2.1
Name: nessus-py
Version: 1.2.1
Summary: Nessus API for Python
Author: karrni
Author-email: karrni@proton.me
Requires-Python: >=3.9,<4.0
Classifier: Programming Language :: Python :: 3
Classifier: Programming Language :: Python :: 3.9
Classifier: Programming Language :: Python :: 3.10
Classifier: Programming Language :: Python :: 3.11
Requires-Dist: defusedxml (>=0.7.1,<0.8.0)
Requires-Dist: pydantic (>=2.4.2,<3.0.0)
Requires-Dist: requests (>=2.31.0,<3.0.0)
Requires-Dist: urllib3 (>=2.0.6,<3.0.0)
